[
    {
        "device_id":  "TECHNOMANCER-Shop",
        "timestamp":  "2025-06-05T03:17:40.9916854+05:00",
        "key_code":  13,
        "key_pressed":  "ENTER",
        "window_title":  "Code - peek.ps1 - Peek - Visual Studio Code [Administrator]"
    },
    {
        "device_id":  "TECHNOMANCER-Shop",
        "timestamp":  "2025-06-05T03:17:42.0658605+05:00",
        "key_code":  86,
        "key_pressed":  "V",
        "window_title":  "Code - peek.ps1 - Peek - Visual Studio Code [Administrator]"
    },
    {
        "device_id":  "TECHNOMANCER-Shop",
        "timestamp":  "2025-06-05T03:17:42.1378667+05:00",
        "key_code":  86,
        "key_pressed":  "V",
        "window_title":  "Code - peek.ps1 - Peek - Visual Studio Code [Administrator]"
    },
    {
        "device_id":  "TECHNOMANCER-Shop",
        "timestamp":  "2025-06-05T03:17:54.5355496+05:00",
        "key_code":  67,
        "key_pressed":  "C",
        "window_title":  "Code - peek.ps1 - Peek - Visual Studio Code [Administrator]"
    },
    {
        "device_id":  "TECHNOMANCER-Shop",
        "timestamp":  "2025-06-05T03:17:54.6026719+05:00",
        "key_code":  67,
        "key_pressed":  "C",
        "window_title":  "Code - peek.ps1 - Peek - Visual Studio Code [Administrator]"
    },
    {
        "device_id":  "TECHNOMANCER-Shop",
        "timestamp":  "2025-06-05T03:18:12.2867421+05:00",
        "key_code":  13,
        "key_pressed":  "ENTER",
        "window_title":  "Code - peek.ps1 - Peek - Visual Studio Code [Administrator]"
    }
]
